LICENSE
MANIFEST.in
README.md
setup.cfg
setup.py
docs/HISTORY.rst
docs/README.rst
mywechat.egg-info/PKG-INFO
mywechat.egg-info/SOURCES.txt
mywechat.egg-info/dependency_links.txt
mywechat.egg-info/requires.txt
mywechat.egg-info/top_level.txt
test/__init__.py
test/fateadm.py
test/rk.py
test/test_api.py
test/test_const.py
test/test_request_gen_hot_url.py
test/test_request_gen_search_article_url.py
test/test_request_gen_search_gzh_url.py
test/test_structuring.py
test/test_tools.py
wechatsogou/__init__.py
wechatsogou/api.py
wechatsogou/const.py
wechatsogou/exceptions.py
wechatsogou/filecache.py
wechatsogou/five.py
wechatsogou/identify_image.py
wechatsogou/request.py
wechatsogou/structuring.py
wechatsogou/tools.py