Metadata-Version: 1.0
Name: mywechat
Version: 0.2
Summary: mywechat
Home-page: https://github.com/wqfff/mywechat.git
Author: wqf
Author-email: UNKNOWN
License: MIT License
Platform: UNKNOWN
